pywaterflood/buckleyleverett.py
pywaterflood/_core.pyi
pywaterflood/aquifer.py
pywaterflood/crm.py
pywaterflood/__init__.py
pywaterflood/multiwellproductivity.py
pywaterflood/_core.abi3.so
pywaterflood/py.typed
pywaterflood-0.3.4.dist-info/RECORD
pywaterflood-0.3.4.dist-info/WHEEL
pywaterflood-0.3.4.dist-info/METADATA
pywaterflood-0.3.4.dist-info/licenses/LICENSE
