Metadata-Version: 2.3
Name: pywaterflood
Version: 0.3.4
Classifier: Programming Language :: Python :: 3
Classifier: License :: OSI Approved :: BSD License
Classifier: Operating System :: OS Independent
Classifier: Development Status :: 4 - Beta
Classifier: Intended Audience :: Science/Research
Classifier: Topic :: Scientific/Engineering
Classifier: Topic :: Scientific/Engineering :: Hydrology
Requires-Dist: numpy >=1.21
Requires-Dist: scipy >=1.4
Requires-Dist: pandas >=1.3.5
Requires-Dist: openpyxl >=3.0.9
Requires-Dist: joblib >=1.1.0
Requires-Dist: pytest >=6.2.5 ; extra == 'test'
Requires-Dist: pytest-cov >=3.0.0 ; extra == 'test'
Requires-Dist: coverage[toml] >=6.3.3 ; extra == 'test'
Requires-Dist: furo ; extra == 'docs'
Requires-Dist: nbsphinx >=0.9 ; extra == 'docs'
Requires-Dist: myst-parser >=0.13 ; extra == 'docs'
Requires-Dist: pandoc >=1.12 ; extra == 'docs'
Requires-Dist: sphinx >=7.0 ; extra == 'docs'
Requires-Dist: sphinx-autoapi ; extra == 'docs'
Requires-Dist: sphinx-copybutton ; extra == 'docs'
Requires-Dist: sphinx-design ; extra == 'docs'
Requires-Dist: sphinx-sitemap ; extra == 'docs'
Requires-Dist: ipykernel ; extra == 'devwork'
Requires-Dist: seaborn ; extra == 'devwork'
Provides-Extra: test
Provides-Extra: docs
Provides-Extra: devwork
License-File: LICENSE
Summary: Physics-inspired waterflood performance modeling
Author-email: Frank Male <frank.male@psu.edu>
Requires-Python: >=3.9
Project-URL: repository, https://github.com/frank1010111/pywaterflood
Project-URL: documentation, https://pywaterflood.readthedocs.io
Project-URL: Bug Tracker, https://github.com/frank1010111/pywaterflood/issues
